MANIFEST.in
dist.bat
dist2.bat
egg.bat
setup.py
setup2.py
Products/__init__.py
Products.FlashVideo.egg-info/PKG-INFO
Products.FlashVideo.egg-info/SOURCES.txt
Products.FlashVideo.egg-info/dependency_links.txt
Products.FlashVideo.egg-info/namespace_packages.txt
Products.FlashVideo.egg-info/not-zip-safe
Products.FlashVideo.egg-info/requires.txt
Products.FlashVideo.egg-info/top_level.txt
Products/FlashVideo/FLVHeader.py
Products/FlashVideo/__init__.py
Products/FlashVideo/config.py
Products/FlashVideo/dependencies.txt
Products/FlashVideo/flowplayer_license.txt
Products/FlashVideo/history.txt
Products/FlashVideo/license.txt
Products/FlashVideo/patches.py
Products/FlashVideo/readme.txt
Products/FlashVideo/refresh.txt
Products/FlashVideo/todo.txt
Products/FlashVideo/utils.py
Products/FlashVideo/validators.py
Products/FlashVideo/version.txt
Products/FlashVideo/Extensions/Install.py
Products/FlashVideo/Extensions/__init__.py
Products/FlashVideo/content/FlashVideo.py
Products/FlashVideo/content/FlashVideoFolder.py
Products/FlashVideo/content/FlashVideoPlaylist.py
Products/FlashVideo/content/__init__.py
Products/FlashVideo/i18n/FlashVideo_plone-pl.po
Products/FlashVideo/i18n/FlashVideo_plone-pt-br.po
Products/FlashVideo/i18n/FlashVideo_plone.pot
Products/FlashVideo/profiles/default/import_steps.xml
Products/FlashVideo/profiles/default/propertiestool.xml
Products/FlashVideo/profiles/default/skins.xml
Products/FlashVideo/profiles/default/types.xml
Products/FlashVideo/profiles/default/types/Flash_Video.xml
Products/FlashVideo/profiles/default/types/Flash_Video_Folder.xml
Products/FlashVideo/profiles/default/types/Flash_Video_Playlist.xml
Products/FlashVideo/skins/FlashVideo/FlowPlayerDark.swf
Products/FlashVideo/skins/FlashVideo/flashvideo_icon.gif
Products/FlashVideo/skins/FlashVideo/flashvideo_icon.gif.metadata
Products/FlashVideo/skins/FlashVideo/flashvideo_view.pt
Products/FlashVideo/skins/FlashVideo/flashvideofolder_icon.gif
Products/FlashVideo/skins/FlashVideo/flashvideofolder_icon.gif.metadata
Products/FlashVideo/skins/FlashVideo/flashvideofolder_view.pt
Products/FlashVideo/skins/FlashVideo/flashvideoplaylist_icon.gif
Products/FlashVideo/skins/FlashVideo/flashvideoplaylist_play.pt
Products/FlashVideo/skins/FlashVideo/flashvideoplaylist_view.pt
