Metadata-Version: 1.0
Name: Products.FlashVideo
Version: 0.9
Summary: Flash Video Plone package
Home-page: http://www.llakomy.com/Projects/flashvideo/
Author: Lukasz Lakomy
Author-email: lukasz@llakomy.com
License: GPL
Keywords: plone zope zope2 flash video multimedia streaming
Platform: UNKNOWN
Classifier: Topic :: Multimedia
Classifier: Topic :: Multimedia :: Video
Classifier: Topic :: Multimedia :: Video :: Display
Classifier: Framework :: Zope2
Classifier: Framework :: Plone
Classifier: Development Status :: 5 - Production/Stable
Classifier: Intended Audience :: Developers
Classifier: License :: OSI Approved
Classifier: License :: OSI Approved :: Zope Public License
Classifier: Natural Language :: English
Classifier: Operating System :: OS Independent
Classifier: Programming Language :: Python
Classifier: Programming Language :: JavaScript
Classifier: Programming Language :: Zope
